yacu.py
src/ML_predictor_backend.py
src/__init__.py
src/bank.py
src/crypto_util.py
src/get_data.py
src/gui.py
src/utils.py
yacu-1.1.0.dist-info/LICENSE
yacu-1.1.0.dist-info/METADATA
yacu-1.1.0.dist-info/WHEEL
yacu-1.1.0.dist-info/entry_points.txt
yacu-1.1.0.dist-info/top_level.txt
yacu-1.1.0.dist-info/RECORD
