Metadata-Version: 2.1
Name: yacu
Version: 1.1.0
Summary: Predict crypto prices with ML.
Home-page: https://github.com/1103s/crypto-bot
Author: Yet Another Crypto Util Team
Author-email: 
License: GPL3
Platform: UNKNOWN
Classifier: Programming Language :: Python :: 3.6
Classifier: Operating System :: OS Independent
Requires-Python: >=3.6
Requires-Dist: PyQt5 (>=5.15.6)
Requires-Dist: art (==5.5)
Requires-Dist: cryptocmd
Requires-Dist: matplotlib (>=3.5.1)
Requires-Dist: numpy (>=1.22.2)
Requires-Dist: pandas (==1.3.5)
Requires-Dist: pyqt5 (>=5.15.6)
Requires-Dist: pyqtgraph (==0.12.4)
Requires-Dist: pyside6 (>=6.2.4)
Requires-Dist: requests (==2.27.1)
Requires-Dist: scikit-learn (==1.0.2)
Requires-Dist: skforecast (>=0.4.1)
Requires-Dist: sphinx-rtd-theme
Requires-Dist: sphinxawesome-theme
Requires-Dist: tk-tools (>=0.15.0)
